[{"name":"lada","model":"vesta","date":"2014"},{"name":"aaaaaaa","model":"aaaaaa","date":"aaaaa"},{"name":"lada","model":"vesta","date":"2014"},{"name":"lada","model":"vesta","date":"2014"},{"name":"lada","model":"vesta","date":"2014"},{"name":"lada","model":"vesta","date":"2014"},{"name":"lada","model":"vesta","date":"2014"},{"name":"lada","model":"vesta","date":"2014"},{"name":"lada","model":"vesta","date":"2014"},{"name":"lada","model":"vesta","date":"2014"},{"name":"lada","model":"vesta","date":"2014"},{"name":"lada","model":"vesta","date":"2014"},{"name":"lada","model":"vesta","date":"2014"},{"name":"lada","model":"vesta","date":"2014"},{"name":"lada","model":"vesta","date":"2014"},{"name":"lada","model":"vesta","date":"2014"},{"name":"lada","model":"vesta","date":"2014"},{"name":"lada","model":"vesta","date":"2014"},{"name":"lada","model":"vesta","date":"2014"},{"name":"lada","model":"vesta","date":"2014"},{"name":"211","model":"12e1","date":"e"},{"name":"eqdq","model":"dq","date":"dqwqdwqd"},{"name":"qdqwdq","model":"wdqqwddqwdw","date":"qwdwqwqd"},{"name":"qdqwdq","model":"wdqqwddqwdw","date":"qwdwqwqd"}]